nnmoduletools/__init__.py
nnmoduletools/comparer/__init__.py
nnmoduletools/comparer/__main__.py
nnmoduletools/comparer/compare_visualizer.py
nnmoduletools/float_utils/__init__.py
nnmoduletools/float_utils/float_utils.py
nnmoduletools/module_debugger/__init__.py
nnmoduletools/module_debugger/module_debugger.py
nnmoduletools/module_debugger/tensor_utils.py
nnmoduletools/module_debugger/utils.py
nnmoduletools-0.2.2.dist-info/METADATA
nnmoduletools-0.2.2.dist-info/WHEEL
nnmoduletools-0.2.2.dist-info/top_level.txt
nnmoduletools-0.2.2.dist-info/RECORD
